csbtest/__init__.py
csbtest/georeference.py
csbtest/uncertainty.py
csbtest-0.1.0.dist-info/LICENSE
csbtest-0.1.0.dist-info/METADATA
csbtest-0.1.0.dist-info/WHEEL
csbtest-0.1.0.dist-info/top_level.txt
csbtest-0.1.0.dist-info/RECORD
